{"updated": "2026-06-26T17:12:39Z", "prices": {"EGEEN.IS": {"price": 5507.5, "change": 107.5, "changePct": 1.9907}, "FROTO.IS": {"price": 86.25, "change": -0.1, "changePct": -0.1158}, "OTKAR.IS": {"price": 366.25, "change": 8.0, "changePct": 2.2331}, "PGSUS.IS": {"price": 180.1, "change": -0.6, "changePct": -0.332}, "BRSAN.IS": {"price": 544.0, "change": -4.5, "changePct": -0.8204}, "CLEBI.IS": {"price": 1603.0, "change": 2.0, "changePct": 0.1249}, "ISMEN.IS": {"price": 36.6, "change": -0.12, "changePct": -0.3268}, "ANSGR.IS": {"price": 28.08, "change": 0.06, "changePct": 0.2141}, "LOGO.IS": {"price": 135.8, "change": -2.2, "changePct": -1.5942}, "SODSN.IS": {"price": 8.55, "change": -0.02, "changePct": -0.2334}, "LKMNH.IS": {"price": 15.54, "change": 0.48, "changePct": 3.1873}, "ALKA.IS": {"price": 9.34, "change": -0.07, "changePct": -0.7439}, "ALTNY.IS": {"price": 15.74, "change": -0.36, "changePct": -2.236}, "THYAO.IS": {"price": 330.75, "change": 2.25, "changePct": 0.6849}, "GARAN.IS": {"price": 138.4, "change": 0.8, "changePct": 0.5814}, "AKBNK.IS": {"price": 77.25, "change": 0.05, "changePct": 0.0648}, "EREGL.IS": {"price": 42.12, "change": 1.8, "changePct": 4.4643}, "BIMAS.IS": {"price": 374.5, "change": -1.0, "changePct": -0.2663}, "KCHOL.IS": {"price": 198.2, "change": 3.3, "changePct": 1.6932}, "SAHOL.IS": {"price": 97.45, "change": 0.45, "changePct": 0.4639}, "ASELS.IS": {"price": 361.5, "change": -12.0, "changePct": -3.2129}, "TOASO.IS": {"price": 325.0, "change": -10.5, "changePct": -3.1297}, "SISE.IS": {"price": 45.32, "change": 1.08, "changePct": 2.4412}, "CCOLA.IS": {"price": 81.25, "change": 2.1, "changePct": 2.6532}, "TTKOM.IS": {"price": 62.25, "change": 1.55, "changePct": 2.5535}, "ARCLK.IS": {"price": 104.1, "change": 4.0, "changePct": 3.996}, "YKBNK.IS": {"price": 40.66, "change": 0.16, "changePct": 0.3951}, "HALKB.IS": {"price": 44.04, "change": 0.94, "changePct": 2.181}, "VAKBN.IS": {"price": 32.96, "change": 0.7, "changePct": 2.1699}, "PETKM.IS": {"price": 19.58, "change": 0.26, "changePct": 1.3458}, "TCELL.IS": {"price": 110.9, "change": 0.4, "changePct": 0.362}, "TUPRS.IS": {"price": 219.2, "change": 0.0, "changePct": 0.0}, "ENKAI.IS": {"price": 90.85, "change": 1.15, "changePct": 1.2821}, "MGROS.IS": {"price": 688.5, "change": -5.5, "changePct": -0.7925}, "OYAKC.IS": {"price": 20.82, "change": 0.24, "changePct": 1.1662}, "DOHOL.IS": {"price": 21.14, "change": 0.26, "changePct": 1.2452}, "VESBE.IS": {"price": 6.73, "change": 0.61, "changePct": 9.9673}, "ULKER.IS": {"price": 102.4, "change": 0.2, "changePct": 0.1957}, "EKGYO.IS": {"price": 20.96, "change": 0.16, "changePct": 0.7692}, "SKBNK.IS": {"price": 15.45, "change": -1.47, "changePct": -8.6879}, "CIMSA.IS": {"price": 49.04, "change": 0.02, "changePct": 0.0408}, "TAVHL.IS": {"price": 284.5, "change": 0.25, "changePct": 0.088}, "AEFES.IS": {"price": 21.26, "change": 0.54, "changePct": 2.6062}, "AGHOL.IS": {"price": 33.06, "change": 0.72, "changePct": 2.2263}, "ALGYO.IS": {"price": 4.03, "change": 0.02, "changePct": 0.4988}, "ALKIM.IS": {"price": 18.04, "change": -0.16, "changePct": -0.8791}, "BANVT.IS": {"price": 176.0, "change": -3.0, "changePct": -1.676}, "BUCIM.IS": {"price": 5.76, "change": -0.02, "changePct": -0.346}, "BRYAT.IS": {"price": 1869.0, "change": 7.0, "changePct": 0.3759}, "CWENE.IS": {"price": 36.8, "change": -0.72, "changePct": -1.919}, "DOAS.IS": {"price": 183.9, "change": -1.1, "changePct": -0.5946}, "DURDO.IS": {"price": 5.26, "change": 0.04, "changePct": 0.7663}, "ENJSA.IS": {"price": 102.7, "change": -0.6, "changePct": -0.5808}, "FENER.IS": {"price": 3.04, "change": -0.02, "changePct": -0.6536}, "GESAN.IS": {"price": 68.65, "change": -1.1, "changePct": -1.5771}, "GUBRF.IS": {"price": 479.75, "change": 2.25, "changePct": 0.4712}, "INDES.IS": {"price": 11.22, "change": -0.08, "changePct": -0.708}, "ISGYO.IS": {"price": 27.3, "change": 2.36, "changePct": 9.4627}, "KONTR.IS": {"price": 3.53, "change": -0.12, "changePct": -3.2877}, "KONYA.IS": {"price": 3760.0, "change": 65.0, "changePct": 1.7591}, "KOPOL.IS": {"price": 7.23, "change": 0.4, "changePct": 5.8565}, "KORDS.IS": {"price": 69.0, "change": -4.0, "changePct": -5.4795}, "KRDMB.IS": {"price": 135.2, "change": 8.2, "changePct": 6.4567}, "KRDMD.IS": {"price": 40.56, "change": 1.16, "changePct": 2.9442}, "MARTI.IS": {"price": 1.76, "change": -0.02, "changePct": -1.1236}, "MAVI.IS": {"price": 39.88, "change": 0.48, "changePct": 1.2183}, "MEDTR.IS": {"price": 28.44, "change": -0.94, "changePct": -3.1995}, "MPARK.IS": {"price": 426.0, "change": -0.5, "changePct": -0.1172}, "NTHOL.IS": {"price": 44.38, "change": -0.86, "changePct": -1.901}, "ODAS.IS": {"price": 8.4, "change": -0.19, "changePct": -2.2119}, "ORGE.IS": {"price": 122.4, "change": 1.0, "changePct": 0.8237}, "PARSN.IS": {"price": 88.05, "change": -1.7, "changePct": -1.8942}, "PRKME.IS": {"price": 20.52, "change": 1.85, "changePct": 9.9089}, "QUAGR.IS": {"price": 3.97, "change": 0.11, "changePct": 2.8497}, "SELEC.IS": {"price": 198.3, "change": -16.6, "changePct": -7.7245}, "SILVR.IS": {"price": 2.74, "change": -0.01, "changePct": -0.3636}, "SMART.IS": {"price": 32.24, "change": 0.36, "changePct": 1.1292}, "SOKM.IS": {"price": 46.78, "change": -0.22, "changePct": -0.4681}, "TKNSA.IS": {"price": 19.93, "change": 0.64, "changePct": 3.3178}, "TKFEN.IS": {"price": 141.7, "change": 8.9, "changePct": 6.7018}, "TMSN.IS": {"price": 89.3, "change": -0.05, "changePct": -0.056}, "TRGYO.IS": {"price": 99.0, "change": -0.15, "changePct": -0.1513}, "TURSG.IS": {"price": 6.3, "change": -0.02, "changePct": -0.3165}, "VESTL.IS": {"price": 26.04, "change": 2.36, "changePct": 9.9662}, "YATAS.IS": {"price": 40.26, "change": 0.4, "changePct": 1.0035}, "USDTRY=X": {"price": 46.6194, "change": 0.0861, "changePct": 0.185}, "EURUSD=X": {"price": 1.1396, "change": 0.0019, "changePct": 0.167}}}